{
  "appId": "com.badran.cnc",
  "appName": "Badran CNC",
  "webDir": ".",
  "server": {
    "androidScheme": "https",
    "allowNavigation": [
      "cmpiielkogwzfhurwqvn.supabase.co",
      "*.supabase.co"
    ]
  },
  "android": {
    "allowMixedContent": true,
    "backgroundColor": "#f8fafc",
    "icon": "logo-badran.png"
  },
  "ios": {
    "contentInset": "always"
  },
  "plugins": {
    "SplashScreen": {
      "launchShowDuration": 2000,
      "backgroundColor": "#f8fafc",
      "showSpinner": false
    }
  }
}